{"children":[{"name":"+2 ELUP.wav","class":"filename","size":1,"color":"+2 ELUP.wav","label":["+2 ELUP.wav"]},{"name":"0304S-FP-451_AntPeninsula_DreamIsEleSeal.WAV","class":"filename","size":1,"color":"0304S-FP-451_AntPeninsula_DreamIsEleSeal.WAV","label":["0304S-FP-451_AntPeninsula_DreamIsEleSeal.WAV"]},{"name":"0305S_AF_DzangaBai_Elephants_20110113_BAI037.wav","class":"filename","size":1,"color":"0305S_AF_DzangaBai_Elephants_20110113_BAI037.wav","label":["0305S_AF_DzangaBai_Elephants_20110113_BAI037.wav"]},{"name":"0404S-FP-019_HudsonBayCanada_PolarBearBreathes.wav","class":"filename","size":1,"color":"0404S-FP-019_HudsonBayCanada_PolarBearBreathes.wav","label":["0404S-FP-019_HudsonBayCanada_PolarBearBreathes.wav"]},{"name":"0606S_AF_Comoros_Atmos_20100929-000017.WAV","class":"filename","size":1,"color":"0606S_AF_Comoros_Atmos_20100929-000017.WAV","label":["0606S_AF_Comoros_Atmos_20100929-000017.WAV"]},{"name":"48 underwater salmon currents.wav","class":"filename","size":1,"color":"48 underwater salmon currents.wav","label":["48 underwater salmon currents.wav"]},{"name":"64 Explosion_Water Splash 01","class":"filename","size":1,"color":"64 Explosion_Water Splash 01","label":["64 Explosion_Water Splash 01"]},{"name":"65 Explosion_Water Splash 02","class":"filename","size":1,"color":"65 Explosion_Water Splash 02","label":["65 Explosion_Water Splash 02"]},{"name":"7ELEMOVE.wav","class":"filename","size":1,"color":"7ELEMOVE.wav","label":["7ELEMOVE.wav"]},{"name":"ADELIE PENGUIN cu calls, moves & running frm several chicks. Gulls in bg. Antarctic.wav","class":"filename","size":1,"color":"ADELIE PENGUIN cu calls, moves & running frm several chicks. Gulls in bg. Antarctic.wav","label":["ADELIE PENGUIN cu calls, moves & running frm several chicks. Gulls in bg. Antarctic.wav"]},{"name":"ADELIE PENGUIN md-cu calls frm adults & chicks. penguin footsteps. colony calls. mixture of chick ages. Antarctica.wav","class":"filename","size":1,"color":"ADELIE PENGUIN md-cu calls frm adults & chicks. penguin footsteps. colony calls. mixture of chick ages. Antarctica.wav","label":["ADELIE PENGUIN md-cu calls frm adults & chicks. penguin footsteps. colony calls. mixture of chick ages. Antarctica.wav"]},{"name":"ADELIE PENGUIN running & alarm calls. Antarctica.wav","class":"filename","size":1,"color":"ADELIE PENGUIN running & alarm calls. Antarctica.wav","label":["ADELIE PENGUIN running & alarm calls. Antarctica.wav"]},{"name":"AERIAL.wav","class":"filename","size":1,"color":"AERIAL.wav","label":["AERIAL.wav"]},{"name":"AIR FAST.wav","class":"filename","size":1,"color":"AIR FAST.wav","label":["AIR FAST.wav"]},{"name":"AIR PAST2.wav","class":"filename","size":1,"color":"AIR PAST2.wav","label":["AIR PAST2.wav"]},{"name":"AT-03_13_01","class":"filename","size":1,"color":"AT-03_13_01","label":["AT-03_13_01"]},{"name":"AZ-04_62_03","class":"filename","size":1,"color":"AZ-04_62_03","label":["AZ-04_62_03"]},{"name":"AZ-04_63_01","class":"filename","size":1,"color":"AZ-04_63_01","label":["AZ-04_63_01"]},{"name":"Above water splashes _00_.L.wav","class":"filename","size":1,"color":"Above water splashes _00_.L.wav","label":["Above water splashes _00_.L.wav"]},{"name":"Above water splashing arms .L","class":"filename","size":1,"color":"Above water splashing arms .L","label":["Above water splashing arms .L"]},{"name":"BEAR BEG.wav","class":"filename","size":1,"color":"BEAR BEG.wav","label":["BEAR BEG.wav"]},{"name":"BEAR BREA.wav","class":"filename","size":1,"color":"BEAR BREA.wav","label":["BEAR BREA.wav"]},{"name":"BEAR CD.wav","class":"filename","size":1,"color":"BEAR CD.wav","label":["BEAR CD.wav"]},{"name":"BEAR CUB.wav","class":"filename","size":1,"color":"BEAR CUB.wav","label":["BEAR CUB.wav"]},{"name":"BEAR CUB3.wav","class":"filename","size":1,"color":"BEAR CUB3.wav","label":["BEAR CUB3.wav"]},{"name":"BEAR ROA1.wav","class":"filename","size":1,"color":"BEAR ROA1.wav","label":["BEAR ROA1.wav"]},{"name":"BEARBREA6.wav","class":"filename","size":1,"color":"BEARBREA6.wav","label":["BEARBREA6.wav"]},{"name":"BEARBREAT.wav","class":"filename","size":1,"color":"BEARBREAT.wav","label":["BEARBREAT.wav"]},{"name":"BIG SPLSH.wav","class":"filename","size":1,"color":"BIG SPLSH.wav","label":["BIG SPLSH.wav"]},{"name":"BISON 3.wav","class":"filename","size":1,"color":"BISON 3.wav","label":["BISON 3.wav"]},{"name":"BLACK OYSTERCATCHER MCU FLIGHT & CONTACT CALLS. BG SURF. ST LAZARIA ALASKA.wav","class":"filename","size":1,"color":"BLACK OYSTERCATCHER MCU FLIGHT & CONTACT CALLS. BG SURF. ST LAZARIA ALASKA.wav","label":["BLACK OYSTERCATCHER MCU FLIGHT & CONTACT CALLS. BG SURF. ST LAZARIA ALASKA.wav"]},{"name":"BODY FALL.wav","class":"filename","size":1,"color":"BODY FALL.wav","label":["BODY FALL.wav"]},{"name":"BODYFALL IN SAND CU_001.wav","class":"filename","size":1,"color":"BODYFALL IN SAND CU_001.wav","label":["BODYFALL IN SAND CU_001.wav"]},{"name":"BODYFALLS.wav","class":"filename","size":1,"color":"BODYFALLS.wav","label":["BODYFALLS.wav"]},{"name":"BRANCHES.wav","class":"filename","size":1,"color":"BRANCHES.wav","label":["BRANCHES.wav"]},{"name":"BassEerieProcess SDT02_98_1.wav","class":"filename","size":1,"color":"BassEerieProcess SDT02_98_1.wav","label":["BassEerieProcess SDT02_98_1.wav"]},{"name":"BigWhip SDT01_24_1.wav","class":"filename","size":1,"color":"BigWhip SDT01_24_1.wav","label":["BigWhip SDT01_24_1.wav"]},{"name":"CLOUD 1.wav","class":"filename","size":1,"color":"CLOUD 1.wav","label":["CLOUD 1.wav"]},{"name":"CLOUDERPT.wav","class":"filename","size":1,"color":"CLOUDERPT.wav","label":["CLOUDERPT.wav"]},{"name":"CLOUDPASS.wav","class":"filename","size":1,"color":"CLOUDPASS.wav","label":["CLOUDPASS.wav"]},{"name":"CLOUDS 1.wav","class":"filename","size":1,"color":"CLOUDS 1.wav","label":["CLOUDS 1.wav"]},{"name":"CLOUDS 2A.wav","class":"filename","size":1,"color":"CLOUDS 2A.wav","label":["CLOUDS 2A.wav"]},{"name":"CONTACT 1.wav","class":"filename","size":1,"color":"CONTACT 1.wav","label":["CONTACT 1.wav"]},{"name":"Claw_Impacts_Scrapes_W_m6ba_01.M.wav","class":"filename","size":1,"color":"Claw_Impacts_Scrapes_W_m6ba_01.M.wav","label":["Claw_Impacts_Scrapes_W_m6ba_01.M.wav"]},{"name":"DESERT WIND MED-01.A1","class":"filename","size":1,"color":"DESERT WIND MED-01.A1","label":["DESERT WIND MED-01.A1"]},{"name":"DOLPHIN SP. school playing around boat mainly spashing, GALAPAGOS SLANDS.wav","class":"filename","size":1,"color":"DOLPHIN SP. school playing around boat mainly spashing, GALAPAGOS SLANDS.wav","label":["DOLPHIN SP. school playing around boat mainly spashing, GALAPAGOS SLANDS.wav"]},{"name":"DRIPS 2.wav","class":"filename","size":1,"color":"DRIPS 2.wav","label":["DRIPS 2.wav"]},{"name":"DRIPS.wav","class":"filename","size":1,"color":"DRIPS.wav","label":["DRIPS.wav"]},{"name":"DROPS.wav","class":"filename","size":1,"color":"DROPS.wav","label":["DROPS.wav"]},{"name":"DUSTDEVIL.wav","class":"filename","size":1,"color":"DUSTDEVIL.wav","label":["DUSTDEVIL.wav"]},{"name":"DreamyWhoosh SDT02_18_1.wav","class":"filename","size":1,"color":"DreamyWhoosh SDT02_18_1.wav","label":["DreamyWhoosh SDT02_18_1.wav"]},{"name":"EK02T37.WAV","class":"filename","size":1,"color":"EK02T37.WAV","label":["EK02T37.WAV"]},{"name":"EK14-66.WAV","class":"filename","size":1,"color":"EK14-66.WAV","label":["EK14-66.WAV"]},{"name":"EK14-68.WAV","class":"filename","size":1,"color":"EK14-68.WAV","label":["EK14-68.WAV"]},{"name":"EK14-72.WAV","class":"filename","size":1,"color":"EK14-72.WAV","label":["EK14-72.WAV"]},{"name":"ELE BABY.wav","class":"filename","size":1,"color":"ELE BABY.wav","label":["ELE BABY.wav"]},{"name":"ELE BATH.wav","class":"filename","size":1,"color":"ELE BATH.wav","label":["ELE BATH.wav"]},{"name":"ELE BATH2.wav","class":"filename","size":1,"color":"ELE BATH2.wav","label":["ELE BATH2.wav"]},{"name":"ELE BUBBL.wav","class":"filename","size":1,"color":"ELE BUBBL.wav","label":["ELE BUBBL.wav"]},{"name":"ELE FEET2.wav","class":"filename","size":1,"color":"ELE FEET2.wav","label":["ELE FEET2.wav"]},{"name":"ELE SNOR4.wav","class":"filename","size":1,"color":"ELE SNOR4.wav","label":["ELE SNOR4.wav"]},{"name":"ELE SNORT.wav","class":"filename","size":1,"color":"ELE SNORT.wav","label":["ELE SNORT.wav"]},{"name":"ELE THU W.wav","class":"filename","size":1,"color":"ELE THU W.wav","label":["ELE THU W.wav"]},{"name":"ELE.DEEPW.wav","class":"filename","size":1,"color":"ELE.DEEPW.wav","label":["ELE.DEEPW.wav"]},{"name":"ELE.WATER.wav","class":"filename","size":1,"color":"ELE.WATER.wav","label":["ELE.WATER.wav"]},{"name":"EXPLOSION   UNDERWATE_MOD.L.wav","class":"filename","size":1,"color":"EXPLOSION   UNDERWATE_MOD.L.wav","label":["EXPLOSION   UNDERWATE_MOD.L.wav"]},{"name":"Elephant growl (M+S).wav","class":"filename","size":1,"color":"Elephant growl (M+S).wav","label":["Elephant growl (M+S).wav"]},{"name":"Elephant, growl, scream and trumpet.wav","class":"filename","size":1,"color":"Elephant, growl, scream and trumpet.wav","label":["Elephant, growl, scream and trumpet.wav"]},{"name":"Elephants eating, loud grunts.wav","class":"filename","size":1,"color":"Elephants eating, loud grunts.wav","label":["Elephants eating, loud grunts.wav"]},{"name":"Elephants, trumpet.wav","class":"filename","size":1,"color":"Elephants, trumpet.wav","label":["Elephants, trumpet.wav"]},{"name":"F 1.wav","class":"filename","size":1,"color":"F 1.wav","label":["F 1.wav"]},{"name":"FINBASS.wav","class":"filename","size":1,"color":"FINBASS.wav","label":["FINBASS.wav"]},{"name":"FISH 1.wav","class":"filename","size":1,"color":"FISH 1.wav","label":["FISH 1.wav"]},{"name":"FISH 13.wav","class":"filename","size":1,"color":"FISH 13.wav","label":["FISH 13.wav"]},{"name":"FISH 3.wav","class":"filename","size":1,"color":"FISH 3.wav","label":["FISH 3.wav"]},{"name":"FISHFAST2.wav","class":"filename","size":1,"color":"FISHFAST2.wav","label":["FISHFAST2.wav"]},{"name":"FLASH.wav","class":"filename","size":1,"color":"FLASH.wav","label":["FLASH.wav"]},{"name":"FLIES SP FLIES BUZZING AROUND ...NEW GUINEA.wav","class":"filename","size":1,"color":"FLIES SP FLIES BUZZING AROUND ...NEW GUINEA.wav","label":["FLIES SP FLIES BUZZING AROUND ...NEW GUINEA.wav"]},{"name":"GRIZGROWL.wav","class":"filename","size":1,"color":"GRIZGROWL.wav","label":["GRIZGROWL.wav"]},{"name":"GRIZZLY.wav","class":"filename","size":1,"color":"GRIZZLY.wav","label":["GRIZZLY.wav"]},{"name":"Gryphon_HugeWingPass1.j_1.L.wav","class":"filename","size":1,"color":"Gryphon_HugeWingPass1.j_1.L.wav","label":["Gryphon_HugeWingPass1.j_1.L.wav"]},{"name":"Gryphonwings_Foley4.Jlb.1.M.wav","class":"filename","size":1,"color":"Gryphonwings_Foley4.Jlb.1.M.wav","label":["Gryphonwings_Foley4.Jlb.1.M.wav"]},{"name":"HARRIS'S HAWK CALLS CU - AGGRESSIVE, THREAT - FRM BIRD IN CAPTIVITY. OTHER SPECIES MP. ARIZONA USA.L.wav","class":"filename","size":1,"color":"HARRIS'S HAWK CALLS CU - AGGRESSIVE, THREAT - FRM BIRD IN CAPTIVITY. OTHER SPECIES MP. ARIZONA USA.L.wav","label":["HARRIS'S HAWK CALLS CU - AGGRESSIVE, THREAT - FRM BIRD IN CAPTIVITY. OTHER SPECIES MP. ARIZONA USA.L.wav"]},{"name":"HIT BATTLE ARMOUR BIG.M.wav","class":"filename","size":1,"color":"HIT BATTLE ARMOUR BIG.M.wav","label":["HIT BATTLE ARMOUR BIG.M.wav"]},{"name":"HOT 1.wav","class":"filename","size":1,"color":"HOT 1.wav","label":["HOT 1.wav"]},{"name":"HOT WIND THROUGH SOFT TREES AERIAL GOOD MAX.wav","class":"filename","size":1,"color":"HOT WIND THROUGH SOFT TREES AERIAL GOOD MAX.wav","label":["HOT WIND THROUGH SOFT TREES AERIAL GOOD MAX.wav"]},{"name":"INDIAN ELEPHANT MCU MD SPLASHES & BUBBLING IN RIVER, LOUD EXHALATIONS, GOOD BREATHING, DIST CALLS BIRDS, OCCASS VOICES BG. MADHYA PRADESH INDIA.wav","class":"filename","size":1,"color":"INDIAN ELEPHANT MCU MD SPLASHES & BUBBLING IN RIVER, LOUD EXHALATIONS, GOOD BREATHING, DIST CALLS BIRDS, OCCASS VOICES BG. MADHYA PRADESH INDIA.wav","label":["INDIAN ELEPHANT MCU MD SPLASHES & BUBBLING IN RIVER, LOUD EXHALATIONS, GOOD BREATHING, DIST CALLS BIRDS, OCCASS VOICES BG. MADHYA PRADESH INDIA.wav"]},{"name":"ISLESEA 1.wav","class":"filename","size":1,"color":"ISLESEA 1.wav","label":["ISLESEA 1.wav"]},{"name":"JET PASSS.wav","class":"filename","size":1,"color":"JET PASSS.wav","label":["JET PASSS.wav"]},{"name":"LETSGO 2.wav","class":"filename","size":1,"color":"LETSGO 2.wav","label":["LETSGO 2.wav"]},{"name":"LETSGO 5.wav","class":"filename","size":1,"color":"LETSGO 5.wav","label":["LETSGO 5.wav"]},{"name":"LIGHTNING CU RIP BY-0.A1","class":"filename","size":1,"color":"LIGHTNING CU RIP BY-0.A1","label":["LIGHTNING CU RIP BY-0.A1"]},{"name":"LIGHTNING,THUNDERPOWE_MOD.L.wav","class":"filename","size":1,"color":"LIGHTNING,THUNDERPOWE_MOD.L.wav","label":["LIGHTNING,THUNDERPOWE_MOD.L.wav"]},{"name":"LIGHTSOUT.wav","class":"filename","size":1,"color":"LIGHTSOUT.wav","label":["LIGHTSOUT.wav"]},{"name":"LargeWaveCrash_LargeWaMOD.L.wav","class":"filename","size":1,"color":"LargeWaveCrash_LargeWaMOD.L.wav","label":["LargeWaveCrash_LargeWaMOD.L.wav"]},{"name":"MARA WILDE RUN ACROSS TRACKS LOTS OF STUFF.wav","class":"filename","size":1,"color":"MARA WILDE RUN ACROSS TRACKS LOTS OF STUFF.wav","label":["MARA WILDE RUN ACROSS TRACKS LOTS OF STUFF.wav"]},{"name":"MAX SNIFF.wav","class":"filename","size":1,"color":"MAX SNIFF.wav","label":["MAX SNIFF.wav"]},{"name":"MOONCLIF1.wav","class":"filename","size":1,"color":"MOONCLIF1.wav","label":["MOONCLIF1.wav"]},{"name":"MOUNTAIN WIND ICELAND-01.A1","class":"filename","size":1,"color":"MOUNTAIN WIND ICELAND-01.A1","label":["MOUNTAIN WIND ICELAND-01.A1"]},{"name":"NEUTRAL.wav","class":"filename","size":1,"color":"NEUTRAL.wav","label":["NEUTRAL.wav"]},{"name":"OPEN ATMOS NOTHING.L","class":"filename","size":1,"color":"OPEN ATMOS NOTHING.L","label":["OPEN ATMOS NOTHING.L"]},{"name":"PAT1 BL11.wav","class":"filename","size":1,"color":"PAT1 BL11.wav","label":["PAT1 BL11.wav"]},{"name":"PAT1 SWIM.wav","class":"filename","size":1,"color":"PAT1 SWIM.wav","label":["PAT1 SWIM.wav"]},{"name":"PE-42_70_03","class":"filename","size":1,"color":"PE-42_70_03","label":["PE-42_70_03"]},{"name":"ProcessedLongBig SDT02_80_1.wav","class":"filename","size":1,"color":"ProcessedLongBig SDT02_80_1.wav","label":["ProcessedLongBig SDT02_80_1.wav"]},{"name":"ProcessedLongBig SDT02_80_5.wav","class":"filename","size":1,"color":"ProcessedLongBig SDT02_80_5.wav","label":["ProcessedLongBig SDT02_80_5.wav"]},{"name":"QUIETISLE.wav","class":"filename","size":1,"color":"QUIETISLE.wav","label":["QUIETISLE.wav"]},{"name":"RIVER WIDE DISTANT SEA NEUTRAL MAX.wav","class":"filename","size":1,"color":"RIVER WIDE DISTANT SEA NEUTRAL MAX.wav","label":["RIVER WIDE DISTANT SEA NEUTRAL MAX.wav"]},{"name":"RobotHydraulic PROD_SY01_55.wav","class":"filename","size":1,"color":"RobotHydraulic PROD_SY01_55.wav","label":["RobotHydraulic PROD_SY01_55.wav"]},{"name":"RobotHydraulic PROD_SY01_58.wav","class":"filename","size":1,"color":"RobotHydraulic PROD_SY01_58.wav","label":["RobotHydraulic PROD_SY01_58.wav"]},{"name":"SEA CLIFF.wav","class":"filename","size":1,"color":"SEA CLIFF.wav","label":["SEA CLIFF.wav"]},{"name":"SEA OPEN.wav","class":"filename","size":1,"color":"SEA OPEN.wav","label":["SEA OPEN.wav"]},{"name":"SEALBLOW2.wav","class":"filename","size":1,"color":"SEALBLOW2.wav","label":["SEALBLOW2.wav"]},{"name":"SHADOW 1.wav","class":"filename","size":1,"color":"SHADOW 1.wav","label":["SHADOW 1.wav"]},{"name":"SHARK.wav","class":"filename","size":1,"color":"SHARK.wav","label":["SHARK.wav"]},{"name":"SHOALFISH.wav","class":"filename","size":1,"color":"SHOALFISH.wav","label":["SHOALFISH.wav"]},{"name":"SHOLE 2.wav","class":"filename","size":1,"color":"SHOLE 2.wav","label":["SHOLE 2.wav"]},{"name":"SHOLE 4.wav","class":"filename","size":1,"color":"SHOLE 4.wav","label":["SHOLE 4.wav"]},{"name":"SI-AP13_17_1","class":"filename","size":1,"color":"SI-AP13_17_1","label":["SI-AP13_17_1"]},{"name":"SI-AP17_12_1","class":"filename","size":1,"color":"SI-AP17_12_1","label":["SI-AP17_12_1"]},{"name":"SI-AP18_1_1","class":"filename","size":1,"color":"SI-AP18_1_1","label":["SI-AP18_1_1"]},{"name":"SI-AP1_17_1","class":"filename","size":1,"color":"SI-AP1_17_1","label":["SI-AP1_17_1"]},{"name":"SI-AP1_2_1","class":"filename","size":1,"color":"SI-AP1_2_1","label":["SI-AP1_2_1"]},{"name":"SNIFFS.wav","class":"filename","size":1,"color":"SNIFFS.wav","label":["SNIFFS.wav"]},{"name":"SNOW BUMP.wav","class":"filename","size":1,"color":"SNOW BUMP.wav","label":["SNOW BUMP.wav"]},{"name":"SPACE 2.wav","class":"filename","size":1,"color":"SPACE 2.wav","label":["SPACE 2.wav"]},{"name":"SPACE AT.wav","class":"filename","size":1,"color":"SPACE AT.wav","label":["SPACE AT.wav"]},{"name":"SPLASHES SWIMMING POOL FOR BEAR AND FISH SEQ. SAFETY.wav","class":"filename","size":1,"color":"SPLASHES SWIMMING POOL FOR BEAR AND FISH SEQ. SAFETY.wav","label":["SPLASHES SWIMMING POOL FOR BEAR AND FISH SEQ. SAFETY.wav"]},{"name":"SPLASHOOF.wav","class":"filename","size":1,"color":"SPLASHOOF.wav","label":["SPLASHOOF.wav"]},{"name":"SPLASHSLO.wav","class":"filename","size":1,"color":"SPLASHSLO.wav","label":["SPLASHSLO.wav"]},{"name":"SPLSHTRSH.wav","class":"filename","size":1,"color":"SPLSHTRSH.wav","label":["SPLSHTRSH.wav"]},{"name":"STAMPEDE.wav","class":"filename","size":1,"color":"STAMPEDE.wav","label":["STAMPEDE.wav"]},{"name":"STARSHOOT.wav","class":"filename","size":1,"color":"STARSHOOT.wav","label":["STARSHOOT.wav"]},{"name":"SUN 1.wav","class":"filename","size":1,"color":"SUN 1.wav","label":["SUN 1.wav"]},{"name":"SUN SLOW1.wav","class":"filename","size":1,"color":"SUN SLOW1.wav","label":["SUN SLOW1.wav"]},{"name":"SUNBOMB 2.wav","class":"filename","size":1,"color":"SUNBOMB 2.wav","label":["SUNBOMB 2.wav"]},{"name":"SUNRISE.wav","class":"filename","size":1,"color":"SUNRISE.wav","label":["SUNRISE.wav"]},{"name":"SUNSPOT 1.wav","class":"filename","size":1,"color":"SUNSPOT 1.wav","label":["SUNSPOT 1.wav"]},{"name":"SUNUP.wav","class":"filename","size":1,"color":"SUNUP.wav","label":["SUNUP.wav"]},{"name":"SWISH.wav","class":"filename","size":1,"color":"SWISH.wav","label":["SWISH.wav"]},{"name":"SWSHLowWhompBys_TR.L","class":"filename","size":1,"color":"SWSHLowWhompBys_TR.L","label":["SWSHLowWhompBys_TR.L"]},{"name":"SWSHWindWhooshes_DVL.L","class":"filename","size":1,"color":"SWSHWindWhooshes_DVL.L","label":["SWSHWindWhooshes_DVL.L"]},{"name":"S_020393.wav","class":"filename","size":1,"color":"S_020393.wav","label":["S_020393.wav"]},{"name":"S_020399.wav","class":"filename","size":1,"color":"S_020399.wav","label":["S_020399.wav"]},{"name":"S_046089_001.wav","class":"filename","size":1,"color":"S_046089_001.wav","label":["S_046089_001.wav"]},{"name":"S_077945_001.wav","class":"filename","size":1,"color":"S_077945_001.wav","label":["S_077945_001.wav"]},{"name":"S_086108.wav","class":"filename","size":1,"color":"S_086108.wav","label":["S_086108.wav"]},{"name":"S_088254_002.wav","class":"filename","size":1,"color":"S_088254_002.wav","label":["S_088254_002.wav"]},{"name":"S_088254_003.wav","class":"filename","size":1,"color":"S_088254_003.wav","label":["S_088254_003.wav"]},{"name":"Slam Cut-White Out1.L","class":"filename","size":1,"color":"Slam Cut-White Out1.L","label":["Slam Cut-White Out1.L"]},{"name":"Slo Undrwater Waves-Const.L","class":"filename","size":1,"color":"Slo Undrwater Waves-Const.L","label":["Slo Undrwater Waves-Const.L"]},{"name":"SmallUnderwaterS SDT02_88_1.wav","class":"filename","size":1,"color":"SmallUnderwaterS SDT02_88_1.wav","label":["SmallUnderwaterS SDT02_88_1.wav"]},{"name":"SmallUnderwaterS SDT02_88_3.wav","class":"filename","size":1,"color":"SmallUnderwaterS SDT02_88_3.wav","label":["SmallUnderwaterS SDT02_88_3.wav"]},{"name":"SnowFallSourcejlb.L","class":"filename","size":1,"color":"SnowFallSourcejlb.L","label":["SnowFallSourcejlb.L"]},{"name":"TAIL WHALE 1.wav","class":"filename","size":1,"color":"TAIL WHALE 1.wav","label":["TAIL WHALE 1.wav"]},{"name":"THRASHY.2.wav","class":"filename","size":1,"color":"THRASHY.2.wav","label":["THRASHY.2.wav"]},{"name":"TIG PANT1.wav","class":"filename","size":1,"color":"TIG PANT1.wav","label":["TIG PANT1.wav"]},{"name":"TUBsplashing individual.1.wav","class":"filename","size":1,"color":"TUBsplashing individual.1.wav","label":["TUBsplashing individual.1.wav"]},{"name":"Thunder Sphere July 2013 000011.wav","class":"filename","size":1,"color":"Thunder Sphere July 2013 000011.wav","label":["Thunder Sphere July 2013 000011.wav"]},{"name":"UNDERWTR3.wav","class":"filename","size":1,"color":"UNDERWTR3.wav","label":["UNDERWTR3.wav"]},{"name":"UW MOVES1.wav","class":"filename","size":1,"color":"UW MOVES1.wav","label":["UW MOVES1.wav"]},{"name":"UW SURFAC.wav","class":"filename","size":1,"color":"UW SURFAC.wav","label":["UW SURFAC.wav"]},{"name":"UW SWIMR1.wav","class":"filename","size":1,"color":"UW SWIMR1.wav","label":["UW SWIMR1.wav"]},{"name":"Underwater-SwirlingPassesjlb.L","class":"filename","size":1,"color":"Underwater-SwirlingPassesjlb.L","label":["Underwater-SwirlingPassesjlb.L"]},{"name":"VOLCANO2.wav","class":"filename","size":1,"color":"VOLCANO2.wav","label":["VOLCANO2.wav"]},{"name":"W Hooves 5.WAV","class":"filename","size":1,"color":"W Hooves 5.WAV","label":["W Hooves 5.WAV"]},{"name":"W Hooves 8.WAV","class":"filename","size":1,"color":"W Hooves 8.WAV","label":["W Hooves 8.WAV"]},{"name":"W Hooves3.WAV","class":"filename","size":1,"color":"W Hooves3.WAV","label":["W Hooves3.WAV"]},{"name":"WATER SplashObjectExit SBPW01_139.wav","class":"filename","size":1,"color":"WATER SplashObjectExit SBPW01_139.wav","label":["WATER SplashObjectExit SBPW01_139.wav"]},{"name":"WATER,OCEAN.L.wav","class":"filename","size":1,"color":"WATER,OCEAN.L.wav","label":["WATER,OCEAN.L.wav"]},{"name":"WATERFALL SURF HONG KONG 2.wav","class":"filename","size":1,"color":"WATERFALL SURF HONG KONG 2.wav","label":["WATERFALL SURF HONG KONG 2.wav"]},{"name":"WAVE CRASHES.wav","class":"filename","size":1,"color":"WAVE CRASHES.wav","label":["WAVE CRASHES.wav"]},{"name":"WAVECRAS1.wav","class":"filename","size":1,"color":"WAVECRAS1.wav","label":["WAVECRAS1.wav"]},{"name":"WAVESPRA2.wav","class":"filename","size":1,"color":"WAVESPRA2.wav","label":["WAVESPRA2.wav"]},{"name":"WAVESPRAY.wav","class":"filename","size":1,"color":"WAVESPRAY.wav","label":["WAVESPRAY.wav"]},{"name":"WD013COLD MOUNTAIN WIND.L","class":"filename","size":1,"color":"WD013COLD MOUNTAIN WIND.L","label":["WD013COLD MOUNTAIN WIND.L"]},{"name":"WEIRD 7.wav","class":"filename","size":1,"color":"WEIRD 7.wav","label":["WEIRD 7.wav"]},{"name":"WHALE GLIDE PAST 1.wav","class":"filename","size":1,"color":"WHALE GLIDE PAST 1.wav","label":["WHALE GLIDE PAST 1.wav"]},{"name":"WHOOSH.wav","class":"filename","size":1,"color":"WHOOSH.wav","label":["WHOOSH.wav"]},{"name":"WHOOSH12.wav","class":"filename","size":1,"color":"WHOOSH12.wav","label":["WHOOSH12.wav"]},{"name":"WHOOSHES.wav","class":"filename","size":1,"color":"WHOOSHES.wav","label":["WHOOSHES.wav"]},{"name":"WILDEBEEST EAST AFRICA 1.wav","class":"filename","size":1,"color":"WILDEBEEST EAST AFRICA 1.wav","label":["WILDEBEEST EAST AFRICA 1.wav"]},{"name":"WIND + SNOW BLUSTER-01.A1","class":"filename","size":1,"color":"WIND + SNOW BLUSTER-01.A1","label":["WIND + SNOW BLUSTER-01.A1"]},{"name":"WIND OPEN SAND.wav","class":"filename","size":1,"color":"WIND OPEN SAND.wav","label":["WIND OPEN SAND.wav"]},{"name":"WINDVICAR.wav","class":"filename","size":1,"color":"WINDVICAR.wav","label":["WINDVICAR.wav"]},{"name":"WINGSMANY.wav","class":"filename","size":1,"color":"WINGSMANY.wav","label":["WINGSMANY.wav"]},{"name":"Waves Medium (Onto Rocks) Waves Breaking Onto Rocks With Close Spray.wav","class":"filename","size":1,"color":"Waves Medium (Onto Rocks) Waves Breaking Onto Rocks With Close Spray.wav","label":["Waves Medium (Onto Rocks) Waves Breaking Onto Rocks With Close Spray.wav"]},{"name":"WindMagicCrystalChimes0.wav","class":"filename","size":1,"color":"WindMagicCrystalChimes0.wav","label":["WindMagicCrystalChimes0.wav"]},{"name":"WindMagicCrystalChimes3.wav","class":"filename","size":1,"color":"WindMagicCrystalChimes3.wav","label":["WindMagicCrystalChimes3.wav"]},{"name":"X RUMBLE CLOUDS GATHER.wav","class":"filename","size":1,"color":"X RUMBLE CLOUDS GATHER.wav","label":["X RUMBLE CLOUDS GATHER.wav"]},{"name":"YAWN 1.wav","class":"filename","size":1,"color":"YAWN 1.wav","label":["YAWN 1.wav"]},{"name":"Z HORROR.wav","class":"filename","size":1,"color":"Z HORROR.wav","label":["Z HORROR.wav"]},{"name":"_64_HeavyWaterRumble,Occa.L.wav","class":"filename","size":1,"color":"_64_HeavyWaterRumble,Occa.L.wav","label":["_64_HeavyWaterRumble,Occa.L.wav"]},{"name":"heavy water churning .L.wav","class":"filename","size":1,"color":"heavy water churning .L.wav","label":["heavy water churning .L.wav"]},{"name":"snake slither R1   25 + 0.L.wav","class":"filename","size":1,"color":"snake slither R1   25 + 0.L.wav","label":["snake slither R1   25 + 0.L.wav"]},{"name":"splash water spray after_.L.wav","class":"filename","size":1,"color":"splash water spray after_.L.wav","label":["splash water spray after_.L.wav"]},{"name":"splashes  bear slowed.wav","class":"filename","size":1,"color":"splashes  bear slowed.wav","label":["splashes  bear slowed.wav"]},{"name":"sub booms.wav","class":"filename","size":1,"color":"sub booms.wav","label":["sub booms.wav"]},{"name":"wave impact v2_01.wav","class":"filename","size":1,"color":"wave impact v2_01.wav","label":["wave impact v2_01.wav"]},{"name":"wave spray 04.L.wav","class":"filename","size":1,"color":"wave spray 04.L.wav","label":["wave spray 04.L.wav"]}]}